LICENSE
README.md
setup.py
Xponge/__init__.py
Xponge/__main__.py
Xponge/build.py
Xponge/load.py
Xponge/process.py
Xponge.egg-info/PKG-INFO
Xponge.egg-info/SOURCES.txt
Xponge.egg-info/dependency_links.txt
Xponge.egg-info/entry_points.txt
Xponge.egg-info/requires.txt
Xponge.egg-info/top_level.txt
Xponge/analysis/__init__.py
Xponge/analysis/md_analysis.py
Xponge/analysis/sasa.py
Xponge/analysis/wham.py
Xponge/assign/__init__.py
Xponge/assign/bond_order.py
Xponge/assign/gasteiger.py
Xponge/assign/phmodel.py
Xponge/assign/resp.py
Xponge/assign/tpacm4/ATOMTYPE.dat
Xponge/assign/tpacm4/CHARGE.dat
Xponge/assign/tpacm4/__init__.py
Xponge/forcefield/__init__.py
Xponge/forcefield/amber/OL15.frcmod
Xponge/forcefield/amber/RNA.mol2
Xponge/forcefield/amber/RSFF2C.dat
Xponge/forcefield/amber/__init__.py
Xponge/forcefield/amber/atomic_ions.mol2
Xponge/forcefield/amber/bsc1.mol2
Xponge/forcefield/amber/bsc1.py
Xponge/forcefield/amber/ff14SB.frcmod
Xponge/forcefield/amber/ff14SB.mol2
Xponge/forcefield/amber/ff14sb.py
Xponge/forcefield/amber/ff19SB.frcmod
Xponge/forcefield/amber/ff19SB.mol2
Xponge/forcefield/amber/ff19sb.py
Xponge/forcefield/amber/gaff.dat
Xponge/forcefield/amber/gaff.py
Xponge/forcefield/amber/gaff2.dat
Xponge/forcefield/amber/ions1lm_126_spce.frcmod
Xponge/forcefield/amber/ions1lm_126_tip3p.frcmod
Xponge/forcefield/amber/ions1lm_126_tip4pew.frcmod
Xponge/forcefield/amber/ions234lm_126_spce.frcmod
Xponge/forcefield/amber/ions234lm_126_tip3p.frcmod
Xponge/forcefield/amber/ions234lm_126_tip4pew.frcmod
Xponge/forcefield/amber/ionsjc_spce.frcmod
Xponge/forcefield/amber/ionsjc_tip3p.frcmod
Xponge/forcefield/amber/ionsjc_tip4pew.frcmod
Xponge/forcefield/amber/lipid14.dat
Xponge/forcefield/amber/lipid14.mol2
Xponge/forcefield/amber/lipid14.py
Xponge/forcefield/amber/lipid17.dat
Xponge/forcefield/amber/lipid17.mol2
Xponge/forcefield/amber/lipid17.py
Xponge/forcefield/amber/ol15.mol2
Xponge/forcefield/amber/ol15.py
Xponge/forcefield/amber/ol3.py
Xponge/forcefield/amber/opc.mol2
Xponge/forcefield/amber/opc.py
Xponge/forcefield/amber/parm10.dat
Xponge/forcefield/amber/parm19.dat
Xponge/forcefield/amber/parmbsc1.frcmod
Xponge/forcefield/amber/rsff2c.py
