Metadata-Version: 2.1
Name: Xponge
Version: 1.4.4
Summary: A Python package to perform pre- and post-processing of molecular simulations
Home-page: https://gitee.com/gao_hyp_xyj_admin/xponge
Author: Yijie Xia
Author-email: yijiexia@pku.edu.cn
Classifier: Programming Language :: Python :: 3 :: Only
Classifier: Development Status :: 5 - Production/Stable
Classifier: Operating System :: OS Independent
Requires-Python: >=3.6
License-File: LICENSE
